edation/__init__.py
edation/container.py
edation/edation.py
edation/service/__init__.py
edation/service/io.py
edation/setup.py
edation/stats/__init__.py
edation/stats/base.py
edation/stats/centrality/__init__.py
edation/stats/centrality/__init__.py:Zone.Identifier
edation/stats/centrality/ttest.py
edation/stats/centrality/ttest.py:Zone.Identifier
edation/stats/correlation/__init__.py
edation/stats/correlation/__init__.py:Zone.Identifier
edation/stats/correlation/pearson.py
edation/stats/correlation/pearson.py:Zone.Identifier
edation/stats/correlation/spearman.py
edation/stats/correlation/spearman.py:Zone.Identifier
edation/stats/descriptive.py
edation/stats/distribution.py
edation/stats/goodness_of_fit/__init__.py
edation/stats/goodness_of_fit/__init__.py:Zone.Identifier
edation/stats/goodness_of_fit/chisquare.py
edation/stats/goodness_of_fit/chisquare.py:Zone.Identifier
edation/stats/goodness_of_fit/ksone.py
edation/stats/goodness_of_fit/ksone.py:Zone.Identifier
edation/stats/goodness_of_fit/kstwo.py
edation/stats/goodness_of_fit/kstwo.py:Zone.Identifier
edation/stats/goodness_of_fit/shapiro.py
edation/stats/goodness_of_fit/shapiro.py:Zone.Identifier
edation/stats/independence/__init__.py
edation/stats/independence/__init__.py:Zone.Identifier
edation/stats/independence/chisquare.py
edation/stats/independence/chisquare.py:Zone.Identifier
edation/stats/profile.py
edation/visual/__init__.py
edation/visual/association.py
edation/visual/base.py
edation/visual/config.py
edation/visual/distribution.py
edation-0.0.6.dist-info/WHEEL
edation-0.0.6.dist-info/METADATA
edation-0.0.6.dist-info/RECORD
